{
    "os": "Darwin-19.6.0-x86_64-i386-64bit",
    "python": "3.7.7",
    "heartbeatAt": "2021-02-22T23:11:23.190404",
    "startedAt": "2021-02-22T23:11:21.820196",
    "docker": null,
    "cpu_count": 8,
    "cuda": null,
    "args": [
        "--dataset_name",
        "adult"
    ],
    "state": "running",
    "codePath": "normalizing_flows/train.py",
    "program": "train.py",
    "git": {
        "remote": "https://github.com/Privacy-Police/Differential-Privacy.git",
        "commit": "830c15060d21c693c9324b89872057b066e014e0"
    },
    "email": "mrathod@uw.edu",
    "root": "/Users/mansirathod/Documents/Github_Repository/Differential-Privacy",
    "host": "Mansis-MacBook-Pro.local",
    "username": "mansirathod",
    "executable": "/Users/mansirathod/anaconda3/bin/python"
}
